{
    "icd10code": "D55.2",
    "type": "subcategory",
    "title": "Anaemia due to disorders of glycolytic enzymes",
    "chapter": "Diseases of the blood and blood-forming organs and certain disorders involving the immune mechanism",
    "chapterCode": "III",
    "block": "Haemolytic anaemias",
    "blockCode": "D55-D59",
    "category": "Anaemia due to enzyme disorders",
    "categoryCode": "D55",
    "subcategory": "D55.2",
    "inclusion": [
        "Anaemia: haemolytic nonspherocytic (hereditary), type II",
        "Anaemia: hexokinase deficiency",
        "Anaemia: pyruvate kinase [PK] deficiency",
        "Anaemia: triose-phosphate isomerase deficiency"
    ],
    "exclusion": [
        "autoimmune disease (systemic) NOS",
        "certain conditions originating in the perinatal period",
        "complications of pregnancy, childbirth and the puerperium",
        "congenital malformations, deformations and chromosomal abnormalities",
        "endocrine, nutritional and metabolic diseases",
        "human immunodeficiency virus [HIV] disease",
        "injury, poisoning and certain other consequences of external causes",
        "neoplasms",
        "symptoms, signs and abnormal clinical and laboratory findings, not elsewhere classified",
        "anaemia NOS"
    ],
    "symptoms": [
        "fatigue",
        "pale skin",
        "rapid heart rate",
        "shortness of breath",
        "dizziness"
    ]
}