{
    "icd10code": "D57.3",
    "type": "subcategory",
    "title": "Sickle-cell trait",
    "chapter": "Diseases of the blood and blood-forming organs and certain disorders involving the immune mechanism",
    "chapterCode": "III",
    "block": "Haemolytic anaemias",
    "blockCode": "D55-D59",
    "category": "Sickle-cell disorders",
    "categoryCode": "D57",
    "subcategory": "D57.3",
    "inclusion": [
        "Hb-S trait",
        "Heterozygous haemoglobin S [HbAS]"
    ],
    "exclusion": [
        "autoimmune disease (systemic) NOS",
        "certain conditions originating in the perinatal period",
        "complications of pregnancy, childbirth and the puerperium",
        "congenital malformations, deformations and chromosomal abnormalities",
        "endocrine, nutritional and metabolic diseases",
        "human immunodeficiency virus [HIV] disease",
        "injury, poisoning and certain other consequences of external causes",
        "neoplasms",
        "symptoms, signs and abnormal clinical and laboratory findings, not elsewhere classified",
        "anaemia NOS"
    ],
    "symptoms": [
        "abdominal pain",
        "fatigue",
        "shortness of breath",
        "rapid heart rate",
        "jaundice"
    ]
}