{
    "icd10code": "R06.4",
    "type": "subcategory",
    "title": "Hyperventilation",
    "chapter": "Symptoms, signs and abnormal clinical and laboratory findings, not elsewhere classified",
    "chapterCode": "XVIII",
    "block": "Symptoms and signs involving the circulatory and respiratory systems",
    "blockCode": "R00-R09",
    "category": "Abnormalities of breathing",
    "categoryCode": "R06",
    "subcategory": "R06.4",
    "inclusion": null,
    "exclusion": [
        "abnormal findings on antenatal screening of mother",
        "certain conditions originating in the perinatal period",
        "respiratory: arrest",
        "respiratory: distress: syndrome of adult",
        "respiratory: distress: in newborn",
        "respiratory: failure",
        "respiratory: failure of newborn",
        "psychogenic hyperventilation"
    ],
    "symptoms": [
        "shortness of breath",
        "difficulty breathing",
        "labored breathing",
        "rapid breathing",
        "shallow breathing"
    ]
}