{
    "icd10code": "P95",
    "type": "category",
    "title": "Fetal death of unspecified cause",
    "chapter": "Certain conditions originating in the perinatal period",
    "chapterCode": "XVI",
    "block": "Other disorders originating in the perinatal period",
    "blockCode": "P90-P96",
    "category": "Fetal death of unspecified cause",
    "categoryCode": "P95",
    "subcategory": "",
    "inclusion": [
        "conditions that have their origin in the perinatal period even though death or morbidity occurs later",
        "Deadborn fetus NOS",
        "Stillbirth NOS"
    ],
    "exclusion": [
        "congenital malformations, deformations and chromosomal abnormalities",
        "endocrine, nutritional and metabolic diseases",
        "injury, poisoning and certain other consequences of external causes",
        "neoplasms",
        "tetanus neonatorum",
        "whooping cough"
    ],
    "symptoms": [
        "stillbirth",
        "absent fetal heartbeat",
        "no signs of life at delivery",
        "intrauterine fetal demise",
        "cessation of fetal movement"
    ]
}