{
    "icd10code": "M31.7",
    "type": "subcategory",
    "title": "Microscopic polyangiitis",
    "chapter": "Diseases of the musculoskeletal system and connective tissue",
    "chapterCode": "XIII",
    "block": "Systemic connective tissue disorders",
    "blockCode": "M30-M36",
    "category": "Other necrotizing vasculopathies",
    "categoryCode": "M31",
    "subcategory": "M31.7",
    "inclusion": [
        "autoimmune disease: NOS",
        "autoimmune disease: systemic",
        "collagen (vascular) disease: NOS",
        "collagen (vascular) disease: systemic",
        "Microscopic polyarteritis"
    ],
    "exclusion": [
        "certain conditions originating in the perinatal period",
        "certain disorders of the temporomandibular joint",
        "certain infectious and parasitic diseases",
        "compartment syndrome",
        "complications of pregnancy, childbirth and the puerperium",
        "congenital malformations, deformations and chromosomal abnormalities",
        "endocrine, nutritional and metabolic diseases",
        "injury, poisoning and certain other consequences of external causes",
        "neoplasms",
        "symptoms, signs and abnormal clinical and laboratory findings, not elsewhere classified",
        "arthropathy in: haematological disorders",
        "arthrosis of spine",
        "polyarteritis nodosa"
    ],
    "symptoms": [
        "fatigue",
        "headache",
        "fever",
        "weight loss",
        "muscle pain"
    ]
}