{
    "icd10code": "Q79.9",
    "type": "subcategory",
    "title": "Congenital malformation of musculoskeletal system, unspecified",
    "chapter": "Congenital malformations, deformations and chromosomal abnormalities",
    "chapterCode": "XVII",
    "block": "Congenital malformations and deformations of the musculoskeletal system",
    "blockCode": "Q65-Q79",
    "category": "Congenital malformations of the musculoskeletal system, not elsewhere classified",
    "categoryCode": "Q79",
    "subcategory": "Q79.9",
    "inclusion": [
        "Congenital: anomaly NOS of musculoskeletal system NOS",
        "Congenital: deformity NOS of musculoskeletal system NOS"
    ],
    "exclusion": [
        "inborn errors of metabolism",
        "congenital (sternomastoid) torticollis"
    ],
    "symptoms": [
        "abdominal wall defect",
        "limb deformities",
        "facial abnormalities",
        "spinal curvature",
        "developmental delay"
    ]
}