{
    "icd10code": "F02.4",
    "type": "subcategory",
    "title": "Dementia in human immunodeficiency virus [HIV] disease",
    "chapter": "Mental and behavioural disorders",
    "chapterCode": "V",
    "block": "Organic, including symptomatic, mental disorders",
    "blockCode": "F00-F09",
    "category": "Dementia in other diseases classified elsewhere",
    "categoryCode": "F02",
    "subcategory": "F02.4",
    "inclusion": [
        "disorders of psychological development"
    ],
    "exclusion": [
        "symptoms, signs and abnormal clinical and laboratory findings, not elsewhere classified"
    ],
    "symptoms": [
        "memory impairment",
        "confusion",
        "disorientation",
        "difficulty with language",
        "personality changes"
    ]
}