{
    "icd10code": "E50.4",
    "type": "subcategory",
    "title": "Vitamin A deficiency with keratomalacia",
    "chapter": "Endocrine, nutritional and metabolic diseases",
    "chapterCode": "IV",
    "block": "Other nutritional deficiencies",
    "blockCode": "E50-E64",
    "category": "Vitamin A deficiency",
    "categoryCode": "E50",
    "subcategory": "E50.4",
    "inclusion": null,
    "exclusion": [
        "complications of pregnancy, childbirth and the puerperium",
        "symptoms, signs and abnormal clinical and laboratory findings, not elsewhere classified",
        "transitory endocrine and metabolic disorders specific to fetus and newborn",
        "diabetes mellitus (in): malnutrition-related",
        "sequelae of vitamin A deficiency"
    ],
    "symptoms": [
        "night blindness",
        "photophobia",
        "abnormalities in color perception",
        "reduced visual acuity",
        "xerophthalmia (dry eyes)"
    ]
}