{
    "icd10code": "T57.0",
    "type": "subcategory",
    "title": "Toxic effect: Arsenic and its compounds",
    "chapter": "Injury, poisoning and certain other consequences of external causes",
    "chapterCode": "XIX",
    "block": "Toxic effects of substances chiefly nonmedicinal as to source",
    "blockCode": "T51-T65",
    "category": "Toxic effect of other inorganic substances",
    "categoryCode": "T57",
    "subcategory": "T57.0",
    "inclusion": null,
    "exclusion": [
        "birth trauma",
        "obstetric trauma",
        "malunion of fracture",
        "nonunion of fracture [pseudarthrosis]",
        "pathological fracture",
        "pathological fracture with osteoporosis",
        "stress fracture",
        "corrosions",
        "localized toxic effects classified elsewhere",
        "respiratory conditions due to external agents"
    ],
    "symptoms": [
        "nausea",
        "vomiting",
        "abdominal pain",
        "diarrhea",
        "confusion"
    ]
}