{
    "icd10code": "Q28.3",
    "type": "subcategory",
    "title": "Other malformations of cerebral vessels",
    "chapter": "Congenital malformations, deformations and chromosomal abnormalities",
    "chapterCode": "XVII",
    "block": "Congenital malformations of the circulatory system",
    "blockCode": "Q20-Q28",
    "category": "Other congenital malformations of circulatory system",
    "categoryCode": "Q28",
    "subcategory": "Q28.3",
    "inclusion": [
        "Congenital: cerebral aneurysm (nonruptured)",
        "Congenital: malformation of cerebral vessels NOS"
    ],
    "exclusion": [
        "inborn errors of metabolism",
        "congenital aneurysm: NOS",
        "congenital aneurysm: coronary",
        "congenital aneurysm: peripheral",
        "congenital aneurysm: pulmonary",
        "congenital aneurysm: retinal",
        "ruptured: cerebral arteriovenous malformation",
        "ruptured: malformation of precerebral vessels"
    ],
    "symptoms": [
        "headaches",
        "seizures",
        "dizziness",
        "vision problems",
        "muscle weakness"
    ]
}