{
    "icd10code": "C67.9",
    "type": "subcategory",
    "title": "Malignant neoplasm: Bladder, unspecified",
    "chapter": "Neoplasms",
    "chapterCode": "II",
    "block": "Malignant neoplasms of urinary tract",
    "blockCode": "C64-C68",
    "category": "Malignant neoplasm of bladder",
    "categoryCode": "C67",
    "subcategory": "C67.9",
    "inclusion": null,
    "exclusion": null,
    "symptoms": [
        "blood in urine",
        "frequent urination",
        "pain during urination",
        "lower back pain",
        "unexplained weight loss"
    ]
}