{
    "icd10code": "F98.1",
    "type": "subcategory",
    "title": "Nonorganic encopresis",
    "chapter": "Mental and behavioural disorders",
    "chapterCode": "V",
    "block": "Behavioural and emotional disorders with onset usually occurring in childhood and adolescence",
    "blockCode": "F90-F98",
    "category": "Other behavioural and emotional disorders with onset usually occurring in childhood and adolescence",
    "categoryCode": "F98",
    "subcategory": "F98.1",
    "inclusion": [
        "disorders of psychological development",
        "Functional encopresis",
        "Incontinence of faeces of nonorganic origin",
        "Psychogenic encopresis"
    ],
    "exclusion": [
        "symptoms, signs and abnormal clinical and laboratory findings, not elsewhere classified",
        "breath-holding spells",
        "gender identity disorder of childhood",
        "Kleine-Levin syndrome",
        "obsessive-compulsive disorder",
        "sleep disorders due to emotional causes",
        "encopresis NOS"
    ],
    "symptoms": [
        "bedwetting",
        "nighttime urination",
        "urine leakage during sleep",
        "involuntary urination",
        "sleep disturbance"
    ]
}